compliance_checker/__init__.py
compliance_checker/_version.py
compliance_checker/acdd.py
compliance_checker/base.py
compliance_checker/cfunits.py
compliance_checker/cfutil.py.bkp
compliance_checker/ioos.py
compliance_checker/runner.py
compliance_checker/suite.py
compliance_checker/util.py
compliance_checker/cf/__init__.py
compliance_checker/cf/appendix_a.py
compliance_checker/cf/appendix_c.py
compliance_checker/cf/appendix_d.py
compliance_checker/cf/appendix_e.py
compliance_checker/cf/appendix_f.py
compliance_checker/cf/cf.py
compliance_checker/cf/cf_1_10.py
compliance_checker/cf/cf_1_11.py
compliance_checker/cf/cf_1_6.py
compliance_checker/cf/cf_1_7.py
compliance_checker/cf/cf_1_8.py
compliance_checker/cf/cf_1_9.py
compliance_checker/cf/cf_base.py
compliance_checker/cf/util.py
compliance_checker/data/cf-standard-name-table.xml
compliance_checker/data/seanames.csv
compliance_checker/data/templates/ccheck.html.j2
compliance_checker/data/templates/ccheck_wrapper.html.j2
compliance_checker/protocols/__init__.py
compliance_checker/protocols/cdl.py
compliance_checker/protocols/erddap.py
compliance_checker/protocols/netcdf.py
compliance_checker/protocols/opendap.py
compliance_checker/protocols/zarr.py
compliance_checker/tests/__init__.py
compliance_checker/tests/conftest.py
compliance_checker/tests/helpers.py
compliance_checker/tests/resources.py
compliance_checker/tests/test_acdd.py
compliance_checker/tests/test_base.py
compliance_checker/tests/test_cf.py
compliance_checker/tests/test_cf_integration.py
compliance_checker/tests/test_cli.py
compliance_checker/tests/test_feature_detection.py
compliance_checker/tests/test_ioos_profile.py
compliance_checker/tests/test_ioos_sos.py
compliance_checker/tests/test_protocols.py
compliance_checker/tests/test_suite.py
compliance_checker/tests/test_util.py
compliance_checker/tests/cassettes/test_erddap.yaml
compliance_checker/tests/cassettes/test_netcdf_content_type.yaml
compliance_checker-5.4.1.dist-info/licenses/LICENSE
compliance_checker-5.4.1.dist-info/METADATA
compliance_checker-5.4.1.dist-info/WHEEL
compliance_checker-5.4.1.dist-info/entry_points.txt
compliance_checker-5.4.1.dist-info/top_level.txt
compliance_checker-5.4.1.dist-info/RECORD
