Metadata-Version: 2.4
Name: compliance-checker
Version: 5.4.1
Summary: Checks Datasets and SOS endpoints for standards compliance
Maintainer: Benjamin Adams, Luke Campbell, Filipe Fernandes
Maintainer-email: Dave Foster <dave@axiomdatascience.com>
License: Apache-2.0
Project-URL: documentation, https://ioos.github.io/compliance-checker
Project-URL: homepage, https://compliance.ioos.us/index.html
Project-URL: repository, https://github.com/ioos/compliance-checker
Classifier: Development Status :: 5 - Production/Stable
Classifier: Intended Audience :: Developers
Classifier: Intended Audience :: Science/Research
Classifier: License :: OSI Approved :: Apache Software License
Classifier: Operating System :: MacOS :: MacOS X
Classifier: Operating System :: Microsoft :: Windows
Classifier: Operating System :: POSIX :: Linux
Classifier: Programming Language :: Python
Classifier: Programming Language :: Python :: 3 :: Only
Classifier: Programming Language :: Python :: 3.10
Classifier: Programming Language :: Python :: 3.11
Classifier: Programming Language :: Python :: 3.12
Classifier: Programming Language :: Python :: 3.13
Classifier: Topic :: Scientific/Engineering
Requires-Python: >=3.10
License-File: LICENSE
Requires-Dist: cf-units>=2; sys_platform != "emscripten"
Requires-Dist: cftime>=1.1
Requires-Dist: isodate>=0.6.1
Requires-Dist: jinja2>=2.7.3
Requires-Dist: lxml>=3.2.1
Requires-Dist: netcdf4>=1.6.4
Requires-Dist: owslib>=0.8.3
Requires-Dist: packaging
Requires-Dist: pendulum>=1.2.4
Requires-Dist: pygeoif>=0.6
Requires-Dist: pyproj>=2.2.1
Requires-Dist: pyudunits2; sys_platform == "emscripten"
Requires-Dist: regex>=2017.7.28
Requires-Dist: requests>=2.2.1
Requires-Dist: setuptools>=15
Requires-Dist: shapely>=1.7.1
Requires-Dist: validators>=0.14.2
Dynamic: license-file
